{
    "22-dars vocabulary":{
        "1":{
            "english": "established",
            "uzbek": "tashkil etilgan"
        },
        "2":{
            "english": "athlete",
            "uzbek": "sportchi"
        },
        "3":{
            "english": "to come true",
            "uzbek": "amalga oshishi"
        },
        "4": {
            "english": "meditation",
            "uzbek": "meditatsiya"
        },
        "5": {
            "english": "childish",
            "uzbek": "bolalarcha, nodon"
        },
        "6": {
            "english": "mind",
            "uzbek": "aql"
        },
        "7": {
            "english": "countryside",
            "uzbek": "qishloq joy"
        },
        "8": {
            "english": "surrounded",
            "uzbek": "o‘ralgan"
        },
        "9": {
            "english": "banks",
            "uzbek": "qirg‘oq"
        },
        "10": {
            "english": "woods",
            "uzbek": "o‘rmon"
        },
        "11": {
            "english": "picked",
            "uzbek": "terdi, tanladi"
        },
        "12": {
            "english": "seasons",
            "uzbek": "fasllar"
        },
        "13": {
            "english": "scenery",
            "uzbek": "manzara"
        },
        "14": {
            "english": "open spaces",
            "uzbek": "ochiq joylar"
        },
        "15": {
            "english": "fresh air",
            "uzbek": "toza havo"
        },
        "16": {
            "english": "in the countryside",
            "uzbek": "qishloq hududida"
        },
        "17": {
            "english": "surrounded by nature",
            "uzbek": "tabiat bilan o‘ralgan"
        },
        "18": {
            "english": "owns",
            "uzbek": "egalik qiladi"
        },
        "19": {
            "english": "keep",
            "uzbek": "saqlamoq"
        },
        "20": {
            "english": "crop",
            "uzbek": "ekin, hosil"
        },
        "21": {
            "english": "farming",
            "uzbek": "dehqonchilik"
        },
        "22": {
            "english": "sunset",
            "uzbek": "quyosh botishi"
        },
        "23": {
            "english": "hill",
            "uzbek": "tepa, qir"
        },
        "24": {
            "english": "valley",
            "uzbek": "vodiy"
        },
        "25": {
            "english": "branches",
            "uzbek": "shoxchalar"
        },
        "26": {
            "english": "fence",
            "uzbek": "to‘siq, devor"
        },
        "27": {
            "english": "farmhouse",
            "uzbek": "ferma uyi"
        },
        "28": {
            "english": "gate",
            "uzbek": "darvoza"
        },
        "29": {
            "english": "footpath",
            "uzbek": "piyoda yo'lagi"
        },
        "30": {
            "english": "field",
            "uzbek": "dala"
        },
        "31": {
            "english": "plants",
            "uzbek": "o'simliklar"
        },
        "32": {
            "english": "hopeless",
            "uzbek": "umidsiz"
        },
        "33": {
            "english": "village",
            "uzbek": "qishloq"
        },
        "34": {
            "english": "away",
            "uzbek": "uzoqqa, nariga"
        },
        "35": {
            "english": "there isn't much to do",
            "uzbek": "bu yerda qilish uchun ko‘p narsa yo‘q"
        },
        "36": {
            "english": "record holder",
            "uzbek": "rekord egasi"
        },
        "37": {
            "english": "achievement",
            "uzbek": "yutuq"
        },
        "38": {
            "english": "chin",
            "uzbek": "iyak"
        },
        "39": {
            "english": "challenging",
            "uzbek": "qiyin, talabchan"
        },
        "40": {
            "english": "grass",
            "uzbek": "o't"
        },
        "41":{
            "english": "leaves",
            "uzbek": "barglar"
        },
        "42":{
            "english": "ground",
            "uzbek": "yer" 
        }
    },
    "irregular verbs 1-30" : {
        "1": {
            "english": "be",
            "uzbek": "was/were, been (bo‘lmoq)"
        },
        "2": {
            "english": "begin",
            "uzbek": "began, begun (boshlamoq)"
        },
        "3": {
            "english": "break",
            "uzbek": "broke, broken (sindirmoq)"
        },
        "4": {
            "english": "bring",
            "uzbek": "brought, brought (olib kelmoq)"
        },
        "5": {
            "english": "build",
            "uzbek": "built, built (qurmoq)"
        },
        "6": {
            "english": "buy",
            "uzbek": "bought, bought (sotib olmoq)"
        },
        "7": {
            "english": "catch",
            "uzbek": "caught, caught (ushlamoq)"
        },
        "8": {
            "english": "come",
            "uzbek": "came, come (kelmoq)"
        },
        "9": {
            "english": "do",
            "uzbek": "did, done (qilmoq)"
        },
        "10": {
            "english": "drink",
            "uzbek": "drank, drunk (ichmoq)"
        },
        "11": {
            "english": "eat",
            "uzbek": "ate, eaten (yemoq)"
        },
        "12": {
            "english": "fall",
            "uzbek": "fell, fallen (yiqilmoq)"
        },
        "13": {
            "english": "feel",
            "uzbek": "felt, felt (his qilmoq)"
        },
        "14": {
            "english": "find",
            "uzbek": "found, found (topmoq)"
        },
        "15": {
            "english": "forget",
            "uzbek": "forgot, forgotten (unutmoq)"
        },
        "16": {
            "english": "get",
            "uzbek": "got, got/gotten (olmoq)"
        },
        "17": {
            "english": "give",
            "uzbek": "gave, given (bermoq)"
        },
        "18": {
            "english": "go",
            "uzbek": "went, gone (bormoq)"
        },
        "19": {
            "english": "have",
            "uzbek": "had, had (ega bo‘lmoq)"
        },
        "20": {
            "english": "hear",
            "uzbek": "heard, heard (eshitmoq)"
        },
        "21": {
            "english": "know",
            "uzbek": "knew, known (bilmoq)"
        },
        "22": {
            "english": "leave",
            "uzbek": "left, left (tark etmoq)"
        },
        "23": {
            "english": "lose",
            "uzbek": "lost, lost (yo‘qotmoq)"
        },
        "24": {
            "english": "make",
            "uzbek": "made, made (yasamoq)"
        },
        "25": {
            "english": "meet",
            "uzbek": "met, met (uchrashmoq)"
        },
        "26": {
            "english": "pay",
            "uzbek": "paid, paid (to‘lamoq)"
        },
        "27": {
            "english": "read",
            "uzbek": "read, read (o‘qimoq)"
        },
        "28": {
            "english": "run",
            "uzbek": "ran, run (yugurmoq)"
        },
        "29": {
            "english": "say",
            "uzbek": "said, said (aytmoq)"
        },
        "30": {
            "english": "see",
            "uzbek": "saw, seen (ko‘rmoq)"
        }
    }
}